{"is_source_file": false, "format": "", "description": "", "external_files": [], "external_methods": [], "published": [], "classes": [], "methods": [], "calls": [], "search-terms": [], "state": 2, "file_id": 3, "knowledge_revision": 9, "git_revision": "8b71c6be48dba38c7bca5ff9ba183d8820e32af8", "hash": "ee63333a4841bf025439c755a74c9881", "format-version": 4, "code-base-name": "chess_database", "filename": "chess_database/db_visualizer/public/index.html", "revision_history": [{"9": "8b71c6be48dba38c7bca5ff9ba183d8820e32af8"}]}